Crypto_Notify-1.0.0.dist-info/METADATA
Crypto_Notify-1.0.0.dist-info/RECORD
Crypto_Notify-1.0.0.dist-info/WHEEL
Crypto_Notify-1.0.0.dist-info/entry_points.txt
Crypto_Notify-1.0.0.dist-info/top_level.txt
cryptonotifier/Main.py
cryptonotifier/__init__.py
