Metadata-Version: 2.1
Name: Crypto-Notify
Version: 1.0.0
Summary: Get the latest rates of popular Cryptocurrencies
Home-page: https://github.com/dushyantRathore/Crypto-Notifier
Author: Dushyant Rathore
Author-email: dushyant.bgs@gmail.com
License: MIT
Keywords: Cryptocurrency notifier
Platform: UNKNOWN
Classifier: Development Status :: 3 - Alpha
Classifier: Environment :: Console
Classifier: Intended Audience :: Developers
Classifier: Intended Audience :: Information Technology
Classifier: Natural Language :: English
Classifier: Topic :: Software Development :: Build Tools
Classifier: License :: OSI Approved :: MIT License
Classifier: Programming Language :: Python :: 3
Classifier: Programming Language :: Python :: 3.5
Requires-Dist: requests (<=2.11.1)
Requires-Dist: beautifulsoup4
Requires-Dist: notify2
